app_lib_py/ClassCurves.py
app_lib_py/ModulePredict.py
app_lib_py/__init__.py
app_lib_py_RachelAlcraft-0.0.0.dist-info/METADATA
app_lib_py_RachelAlcraft-0.0.0.dist-info/WHEEL
app_lib_py_RachelAlcraft-0.0.0.dist-info/top_level.txt
app_lib_py_RachelAlcraft-0.0.0.dist-info/RECORD
