Metadata-Version: 2.1
Name: app_lib_py_RachelAlcraft
Version: 0.0.0
Summary: Example library for scientific software.
Home-page: https://github.com/RachelAlcraft/app-lib-py
Author: Rachel Alcraft
Author-email: rachelalcraft@gmail.com
Project-URL: Bug Tracker, https://github.com/RachelAlcraft/app-lib-py/issues
Classifier: Programming Language :: Python :: 3
Classifier: License :: OSI Approved :: MIT License
Classifier: Operating System :: OS Independent
Requires-Python: >=3.6
